pygrader_utils/__init__.py
pygrader_utils/info_widget.py
pygrader_utils/mc_widget.py
pygrader_utils/misc.py
pygrader_utils/multi_select_base.py
pygrader_utils/reading_base.py
pygrader_utils/reading_widget.py
pygrader_utils/select_base.py
pygrader_utils/select_many_widget.py
pygrader_utils/telemetry.py
pygrader_utils/types_widget.py
pygrader_utils/validate.py
pygrader_utils-0.1.0.dist-info/METADATA
pygrader_utils-0.1.0.dist-info/WHEEL
pygrader_utils-0.1.0.dist-info/top_level.txt
pygrader_utils-0.1.0.dist-info/RECORD
