Metadata-Version: 2.1
Name: pygrader-utils
Version: 0.1.0
Summary: Utils for ENGR 131
Author-email: Theo Beers <theo.beers@drexel.edu>
License: MIT
Requires-Python: >=3.11
Requires-Dist: ipython>=8.30.0
Requires-Dist: numpy>=2.1.3
Requires-Dist: panel>=1.5.4
Requires-Dist: pynacl>=1.5.0
Requires-Dist: requests>=2.32.3
Provides-Extra: dev
Requires-Dist: build>=1.2.2.post1; extra == "dev"
Requires-Dist: mypy>=1.13.0; extra == "dev"
Requires-Dist: ruff>=0.8.1; extra == "dev"
Requires-Dist: twine>=6.0.1; extra == "dev"
Requires-Dist: types-requests>=2.32.0.20241016; extra == "dev"
